Metadata-Version: 2.1
Name: NQPV
Version: 0.4b1
Summary: An assistant tool for the formal verification of nondeterministic quantum programs.
Home-page: https://github.com/LucianoXu/NQPV
Author: Yingte Xu
Author-email: lucianoxu@foxmail.com
Keywords: quantum programs,program verification,automatic theorem proving
Platform: Windows
Platform: Linux
Platform: MacOS
Classifier: Environment :: Console
Classifier: License :: OSI Approved :: Apache Software License
Classifier: Intended Audience :: Developers
Classifier: Intended Audience :: Science/Research
Classifier: Development Status :: 4 - Beta
Classifier: Natural Language :: English
Classifier: Programming Language :: Python :: 3
Classifier: Topic :: Scientific/Engineering
License-File: LICENSE
License-File: NOTICE
Requires-Dist: numpy
Requires-Dist: cvxpy
Requires-Dist: ply
